[
  {
    "date": "2023-01-03",
    "open": 118.47,
    "high": 118.8,
    "low": 104.64,
    "close": 108.1,
    "volume": 358126100,
    "support": [100, 95, 90],
    "resistance": [120, 125, 130]
  },
  {
    "date": "2023-01-04",
    "open": 106.54,
    "high": 109.9,
    "low": 101.88,
    "close": 108.1,
    "volume": 319335300,
    "support": [100, 95, 90],
    "resistance": [110, 115, 120]
  },
  {
    "date": "2023-01-05",
    "open": 103.75,
    "high": 108.04,
    "low": 100.2,
    "close": 110.34,
    "volume": 340929700,
    "support": [100, 95, 90],
    "resistance": [115, 120, 125]
  },
  {
    "date": "2023-01-06",
    "open": 108.2,
    "high": 115.8,
    "low": 105.63,
    "close": 113.64,
    "volume": 365480700,
    "support": [105, 100, 95],
    "resistance": [120, 125, 130]
  },
  {
    "date": "2023-01-09",
    "open": 116.25,
    "high": 120.67,
    "low": 111.69,
    "close": 119.77,
    "volume": 365480700,
    "support": [110, 105, 100],
    "resistance": [125, 130, 135]
  }
]
